{"mean":{"confidence_interval":{"confidence_level":0.95,"lower_bound":42970.105875045,"upper_bound":43158.63017042422},"point_estimate":43062.4944497867,"standard_error":48.14267205992843},"median":{"confidence_interval":{"confidence_level":0.95,"lower_bound":42962.22260869565,"upper_bound":43154.188405797104},"point_estimate":43100.89982114345,"standard_error":45.56720963573411},"median_abs_dev":{"confidence_interval":{"confidence_level":0.95,"lower_bound":294.2875352821856,"upper_bound":507.88271813415037},"point_estimate":378.4184131136968,"standard_error":57.13713067383339},"slope":{"confidence_interval":{"confidence_level":0.95,"lower_bound":43080.60769227569,"upper_bound":43212.48229171827},"point_estimate":43149.289030525375,"standard_error":33.729232334441214},"std_dev":{"confidence_interval":{"confidence_level":0.95,"lower_bound":381.57508640200547,"upper_bound":586.6718305449002},"point_estimate":485.24688073995907,"standard_error":52.62033163512713}}